MANIFEST.in
README.md
requirements.txt
setup.py
nuxt/__init__.py
nuxt/__main__.py
nuxt/__main_gunicorn.py
nuxt/__main_uvicorn.py
nuxt/app.py
nuxt/datastructures.py
nuxt/exceptions.py
nuxt/openapi.py
nuxt/reloader.py
nuxt/requests.py
nuxt/responses.py
nuxt/routing.py
nuxt/staticfiles.py
nuxt/templating.py
nuxt/utils.py
nuxt.egg-info/PKG-INFO
nuxt.egg-info/SOURCES.txt
nuxt.egg-info/dependency_links.txt
nuxt.egg-info/entry_points.txt
nuxt.egg-info/not-zip-safe
nuxt.egg-info/requires.txt
nuxt.egg-info/top_level.txt
nuxt/asyncio/__init__.py
nuxt/asyncio/proxies/README.md
nuxt/asyncio/proxies/__init__.py
nuxt/asyncio/proxies/context.py
nuxt/asyncio/proxies/http.py
nuxt/asyncio/proxies/streams.py
nuxt/asyncio/proxies/websocket.py
nuxt/asyncio/repositorys/__init__.py
nuxt/asyncio/repositorys/validation.py
nuxt/repositorys/__init__.py
nuxt/repositorys/empty.py
nuxt/repositorys/validation.py